LICENSE
README.rst
pytest_ads_testplan.py
setup.py
pytest_ads_testplan.egg-info/PKG-INFO
pytest_ads_testplan.egg-info/SOURCES.txt
pytest_ads_testplan.egg-info/dependency_links.txt
pytest_ads_testplan.egg-info/entry_points.txt
pytest_ads_testplan.egg-info/requires.txt
pytest_ads_testplan.egg-info/top_level.txt